complexity_meter/__init__.py
complexity_meter/main.py
complexity_meter/structs.py
complexity_meter/plugins/__init__.py
complexity_meter/plugins/base.py
complexity_meter/plugins/api/__init__.py
complexity_meter/plugins/api/fastapi.py
complexity_meter/plugins/mq/__init__.py
complexity_meter/plugins/mq/faststream.py
complexity_meter-0.0.1.dist-info/licenses/LICENSE
complexity_meter-0.0.1.dist-info/METADATA
complexity_meter-0.0.1.dist-info/WHEEL
complexity_meter-0.0.1.dist-info/entry_points.txt
complexity_meter-0.0.1.dist-info/top_level.txt
complexity_meter-0.0.1.dist-info/RECORD
