Metadata-Version: 2.4
Name: complexity-meter
Version: 0.0.1
Summary: Script to track python project complexity
Author-email: Oleg Strizhechenko <oleg.strizhechenko@gmail.com>
License-Expression: MIT
Project-URL: Homepage, https://codeberg.org/strizhechenko/complexity-meter
Keywords: python,complexity,analyzer,statistics
Requires-Python: >=3.10
License-File: LICENSE
Requires-Dist: toml; python_version < "3.11"
Provides-Extra: test
Requires-Dist: pytest; extra == "test"
Provides-Extra: dev
Requires-Dist: pylint; extra == "dev"
Dynamic: license-file
